LICENSE
MANIFEST.in
README.md
setup.cfg
setup.py
versioneer.py
baseapp_for_restapi_backend_with_swagger/AppObj.py
baseapp_for_restapi_backend_with_swagger/FlaskRestSubclass.py
baseapp_for_restapi_backend_with_swagger/GlobalParamaters.py
baseapp_for_restapi_backend_with_swagger/VaultClient.py
baseapp_for_restapi_backend_with_swagger/__init__.py
baseapp_for_restapi_backend_with_swagger/_version.py
baseapp_for_restapi_backend_with_swagger/apiSecurity.py
baseapp_for_restapi_backend_with_swagger/apidoc.py
baseapp_for_restapi_backend_with_swagger/pip-selfcheck.json
baseapp_for_restapi_backend_with_swagger/requestHelper.py
baseapp_for_restapi_backend_with_swagger/serverInfoAPI.py
baseapp_for_restapi_backend_with_swagger/uniqueCommaSeperatedList.py
baseapp_for_restapi_backend_with_swagger/utils.py
baseapp_for_restapi_backend_with_swagger/webfrontendAPI.py
baseapp_for_restapi_backend_with_swagger.egg-info/PKG-INFO
baseapp_for_restapi_backend_with_swagger.egg-info/SOURCES.txt
baseapp_for_restapi_backend_with_swagger.egg-info/dependency_links.txt
baseapp_for_restapi_backend_with_swagger.egg-info/not-zip-safe
baseapp_for_restapi_backend_with_swagger.egg-info/requires.txt
baseapp_for_restapi_backend_with_swagger.egg-info/top_level.txt
baseapp_for_restapi_backend_with_swagger/bin/activate
baseapp_for_restapi_backend_with_swagger/bin/activate.csh
baseapp_for_restapi_backend_with_swagger/bin/activate.fish
baseapp_for_restapi_backend_with_swagger/bin/activate_this.py
baseapp_for_restapi_backend_with_swagger/bin/easy_install
baseapp_for_restapi_backend_with_swagger/bin/easy_install-3.5
baseapp_for_restapi_backend_with_swagger/bin/pip
baseapp_for_restapi_backend_with_swagger/bin/pip3
baseapp_for_restapi_backend_with_swagger/bin/pip3.5
baseapp_for_restapi_backend_with_swagger/bin/python
baseapp_for_restapi_backend_with_swagger/bin/python-config
baseapp_for_restapi_backend_with_swagger/bin/python3
baseapp_for_restapi_backend_with_swagger/bin/python3.5
baseapp_for_restapi_backend_with_swagger/bin/wheel
baseapp_for_restapi_backend_with_swagger/static/bower/swagger-ui/dist/README.md
baseapp_for_restapi_backend_with_swagger/static/bower/swagger-ui/dist/absolute-path.js
baseapp_for_restapi_backend_with_swagger/static/bower/swagger-ui/dist/droid-sans.css
baseapp_for_restapi_backend_with_swagger/static/bower/swagger-ui/dist/favicon-16x16.png
