Metadata-Version: 2.4
Name: baseapp_for_restapi_backend_with_swagger
Version: 0.5.41
Summary: Python package which provides a base application class for an app with a restapi backend that provides a swagger
Home-page: https://github.com/rmetcalf9/baseapp_for_restapi_backend_with_swagger
Author: Robert Metcalf
Author-email: rmetcalf9@googlemail.com
License: MIT
License-File: LICENSE
Requires-Dist: pytz==2025.2
Requires-Dist: flask==3.1.2
Requires-Dist: flask_restx==1.3.0
Requires-Dist: python-dateutil==2.8.1
Requires-Dist: sortedcontainers==2.4.0
Requires-Dist: bcrypt==3.1.5
Requires-Dist: pyjwt==2.8.0
Requires-Dist: hvac==2.4.0
Dynamic: author
Dynamic: author-email
Dynamic: home-page
Dynamic: license
Dynamic: license-file
Dynamic: requires-dist
Dynamic: summary
